{
	"cnn": {
		"link": "http://edition.cnn.com/"
	},
	"bbc": {
		"link": "http://www.bbc.com/"
	},
	"theguardian": {
		"link": "https://www.theguardian.com/international"
	},
  "breitbart": {
    "link": "http://www.breitbart.com/"
  },
  "infowars": {
    "link": "https://www.infowars.com/"
  },
  "foxnews": {
    "link": "http://www.foxnews.com/"
  },
  "nbcnews": {
    "link": "http://www.nbcnews.com/"
  },
  "washingtonpost": {
    "link": "https://www.washingtonpost.com/"
  },
	"cbsnews": {
		"link": "https://www.cbsnews.com"
	},
	"abcnews": {
		"link": "http://www.abc.net.au"
	},
	"rtnews": {
		"link": "https://www.rt.com"
	},
	"canoe":  {
		"link": "http://www.canoe.com"
	},
	"RussianNewsAgency": {
		"link": "http://www.tass.com"
	},
	"Sputnik": {
		"link": "https://www.sputniknews.com"
	},
	"AssociatedPress": {
		"link": "https://apnews.com"
	}
}
